keboola_mcp_server/__init__.py
keboola_mcp_server/__main__.py
keboola_mcp_server/cli.py
keboola_mcp_server/config.py
keboola_mcp_server/errors.py
keboola_mcp_server/generate_tool_docs.py
keboola_mcp_server/links.py
keboola_mcp_server/mcp.py
keboola_mcp_server/oauth.py
keboola_mcp_server/preview.py
keboola_mcp_server/server.py
keboola_mcp_server/workspace.py
keboola_mcp_server/clients/__init__.py
keboola_mcp_server/clients/ai_service.py
keboola_mcp_server/clients/base.py
keboola_mcp_server/clients/client.py
keboola_mcp_server/clients/data_science.py
keboola_mcp_server/clients/encryption.py
keboola_mcp_server/clients/jobs_queue.py
keboola_mcp_server/clients/query.py
keboola_mcp_server/clients/scheduler.py
keboola_mcp_server/clients/storage.py
keboola_mcp_server/prompts/__init__.py
keboola_mcp_server/prompts/add_prompts.py
keboola_mcp_server/prompts/keboola_prompts.py
keboola_mcp_server/resources/__init__.py
keboola_mcp_server/resources/conditional-flow-schema.json
keboola_mcp_server/resources/flow-schema.json
keboola_mcp_server/resources/storage-schema.json
keboola_mcp_server/resources/data_app/__init__.py
keboola_mcp_server/resources/data_app/qsapi_query_data_code.py
keboola_mcp_server/resources/data_app/sapi_query_data_code.py
keboola_mcp_server/resources/flow_examples/conditional_flow_examples.jsonl
keboola_mcp_server/resources/flow_examples/legacy_flow_examples.jsonl
keboola_mcp_server/resources/prompts/__init__.py
keboola_mcp_server/resources/prompts/project_system_prompt.md
keboola_mcp_server/tools/__init__.py
keboola_mcp_server/tools/constants.py
keboola_mcp_server/tools/data_apps.py
keboola_mcp_server/tools/doc.py
keboola_mcp_server/tools/jobs.py
keboola_mcp_server/tools/oauth.py
keboola_mcp_server/tools/project.py
keboola_mcp_server/tools/search.py
keboola_mcp_server/tools/sql.py
keboola_mcp_server/tools/storage.py
keboola_mcp_server/tools/validation.py
keboola_mcp_server/tools/components/__init__.py
keboola_mcp_server/tools/components/api_models.py
keboola_mcp_server_fastmcp-1.38.1.dist-info/METADATA
keboola_mcp_server_fastmcp-1.38.1.dist-info/WHEEL
keboola_mcp_server_fastmcp-1.38.1.dist-info/entry_points.txt
keboola_mcp_server_fastmcp-1.38.1.dist-info/licenses/LICENSE
keboola_mcp_server_fastmcp-1.38.1.dist-info/RECORD
