Metadata-Version: 2.4
Name: keboola-mcp-server-fastmcp
Version: 1.38.1
Summary: MCP server for interacting with Keboola Connection
Project-URL: Homepage, https://github.com/fastmcp-me/mcp-server-keboola#readme
Project-URL: Repository, https://github.com/fastmcp-me/mcp-server-keboola.git
Project-URL: Issues, https://github.com/fastmcp-me/mcp-server-keboola/issues
Author-email: Keboola <devel@keboola.com>
License-Expression: MIT
License-File: LICENSE
Requires-Python: >=3.10
Requires-Dist: cryptography~=46.0
Requires-Dist: fastmcp==2.14.1
Requires-Dist: httpx~=0.28
Requires-Dist: json-log-formatter~=1.1
Requires-Dist: jsonpath-ng~=1.7
Requires-Dist: jsonschema~=4.25
Requires-Dist: mcp==1.24.0
Requires-Dist: pydantic~=2.12
Requires-Dist: pyjwt~=2.10
Requires-Dist: pyyaml~=6.0
Requires-Dist: sqlglot~=28.5
Requires-Dist: toon-format~=0.9.0b1
Provides-Extra: codestyle
Requires-Dist: black~=25.11; extra == 'codestyle'
Requires-Dist: flake8-bugbear~=25.11; extra == 'codestyle'
Requires-Dist: flake8-colors~=0.1; extra == 'codestyle'
Requires-Dist: flake8-isort~=7.0; extra == 'codestyle'
Requires-Dist: flake8-pyproject~=1.2; extra == 'codestyle'
Requires-Dist: flake8-pytest-style~=2.2; extra == 'codestyle'
Requires-Dist: flake8-quotes~=3.4; extra == 'codestyle'
Requires-Dist: flake8-typing-imports~=1.17; extra == 'codestyle'
Requires-Dist: flake8~=7.3; extra == 'codestyle'
Requires-Dist: isort~=7.0; extra == 'codestyle'
Requires-Dist: pep8-naming~=0.15; extra == 'codestyle'
Provides-Extra: dev
Requires-Dist: tox~=4.32; extra == 'dev'
Provides-Extra: integtests
Requires-Dist: kbcstorage~=0.9; extra == 'integtests'
Provides-Extra: tests
Requires-Dist: pytest-asyncio~=1.3; extra == 'tests'
Requires-Dist: pytest-cov~=7.0; extra == 'tests'
Requires-Dist: pytest-datadir~=1.8; extra == 'tests'
Requires-Dist: pytest-mock~=3.15; extra == 'tests'
Requires-Dist: pytest~=9.0; extra == 'tests'
Requires-Dist: python-dateutil~=2.9; extra == 'tests'
Requires-Dist: python-dotenv~=1.2; extra == 'tests'
